stream_zipper/__init__.py
stream_zipper/exceptions.py
stream_zipper/zipstream.py
stream_zipper-1.0.1.dist-info/LICENSE
stream_zipper-1.0.1.dist-info/METADATA
stream_zipper-1.0.1.dist-info/WHEEL
stream_zipper-1.0.1.dist-info/top_level.txt
stream_zipper-1.0.1.dist-info/RECORD
