Metadata-Version: 2.1
Name: stream-zipper
Version: 1.0.1
Summary: Package which allows you to take several file streams and turn them into a single zipfile stream
Home-page: https://github.com/MauriceBenink/python_stream_zipper
Author: Maurice Benink
Author-email: MauriceBenink@hotmail.com
License: BSD-3-Clause
Platform: UNKNOWN
Classifier: Programming Language :: Python :: 3
Classifier: License :: OSI Approved :: MIT License
Classifier: Operating System :: OS Independent
Requires-Python: >=3.6
Requires-Dist: io
Requires-Dist: itertools
Requires-Dist: zipfile
